linknote/__init__.py
linknote/__main__.py
linknote/cli.py
linknote/server.py
linknote/static/data.js
linknote/static/index.html
linknote/static/script.js
linknote/static/style.css
linknote-0.1.1.dist-info/licenses/LICENSE
linknote-0.1.1.dist-info/METADATA
linknote-0.1.1.dist-info/WHEEL
linknote-0.1.1.dist-info/entry_points.txt
linknote-0.1.1.dist-info/top_level.txt
linknote-0.1.1.dist-info/RECORD
