Metadata-Version: 2.4
Name: linknote
Version: 0.1.1
Summary: A web-based short note manager with search and tagging capabilities
Home-page: https://github.com/sxwxs/linknote
Author: sxwxs
License: MIT
Project-URL: Bug Reports, https://github.com/sxwxs/linknote/issues
Project-URL: Source Code, https://github.com/sxwxs/linknote
Keywords: bookmarks,notes,web application,tagging,search,flask
Classifier: Development Status :: 4 - Beta
Classifier: Intended Audience :: End Users/Desktop
Classifier: License :: OSI Approved :: MIT License
Classifier: Programming Language :: Python :: 3
Requires-Python: >=3.7
License-File: LICENSE
Requires-Dist: flask>=2.0.0
Requires-Dist: werkzeug>=2.0.0
Requires-Dist: click>=7.0
Requires-Dist: PyYAML>=6.0
Requires-Dist: qrcode>=7.0
Requires-Dist: captcha>=0.6.0
Dynamic: author
Dynamic: classifier
Dynamic: description
Dynamic: description-content-type
Dynamic: home-page
Dynamic: keywords
Dynamic: license
Dynamic: license-file
Dynamic: project-url
Dynamic: requires-dist
Dynamic: requires-python
Dynamic: summary
